Metadata-Version: 2.4
Name: texttoknowledgegraph
Version: 0.4.3
Summary: A Python package to generate BEL statements and CX2 networks.
Author-email: Favour James <favour.ujames196@gmail.com>
Project-URL: Homepage, https://github.com/ndexbio/llm-text-to-knowledge-graph
Classifier: Programming Language :: Python :: 3
Classifier: License :: OSI Approved :: MIT License
Classifier: Operating System :: OS Independent
Requires-Python: >=3.11
License-File: LICENSE
Requires-Dist: langchain==0.3.25
Requires-Dist: langchain_core==0.3.60
Requires-Dist: langchain_openai==0.3.17
Requires-Dist: lxml==5.2.1
Requires-Dist: ndex2<4.0.0,>=3.8.0
Requires-Dist: pandas
Requires-Dist: openai==1.79.0
Requires-Dist: pydantic==2.11.4
Requires-Dist: pytest==7.4.4
Requires-Dist: python-dotenv==1.1.0
Requires-Dist: Requests==2.32.3
Requires-Dist: gilda==1.4.0
Requires-Dist: markitdown[all]
Requires-Dist: nltk
Dynamic: license-file
